{"0":{"player_id":0,"player_name":"Eden Hazard","vaep_value":0.0137728072,"offensive_value":0.0234037121,"defensive_value":-0.0096309049,"count":4},"1":{"player_id":3324,"player_name":"Francesc F\u00e0bregas i Soler","vaep_value":-0.0126574754,"offensive_value":-0.0091763986,"defensive_value":-0.0034810768,"count":2},"2":{"player_id":3350,"player_name":"C\u00e9sar Azpilicueta Tanco","vaep_value":0.0795496902,"offensive_value":0.0904717166,"defensive_value":-0.0109220264,"count":59},"3":{"player_id":3360,"player_name":"Francesc F\u00e0bregas i Soler","vaep_value":0.0083823077,"offensive_value":0.0070030933,"defensive_value":0.0013792145,"count":51},"4":{"player_id":3429,"player_name":"C\u00e9sar Azpilicueta Tanco","vaep_value":0.0854160881,"offensive_value":0.0857999457,"defensive_value":-0.0003838576,"count":52},"5":{"player_id":8032,"player_name":"Thibaut Courtois","vaep_value":-0.0273821725,"offensive_value":-0.0118551051,"defensive_value":-0.0155270675,"count":50},"6":{"player_id":8277,"player_name":"Marcos  Alonso Mendoza","vaep_value":0.1025637167,"offensive_value":0.1103399919,"defensive_value":-0.0077762752,"count":121},"7":{"player_id":8317,"player_name":"Nicol\u00e1s Hern\u00e1n Otamendi","vaep_value":-0.0096417955,"offensive_value":0.0130136192,"defensive_value":-0.0226554147,"count":137},"8":{"player_id":8325,"player_name":"Bernardo Mota Veiga de Carvalho e Silva","vaep_value":-0.1078071253,"offensive_value":-0.1168385409,"defensive_value":0.0090314156,"count":30},"9":{"player_id":8495,"player_name":"Andreas Christensen","vaep_value":-0.0413161704,"offensive_value":-0.0314391979,"defensive_value":-0.0098769724,"count":48},"10":{"player_id":8625,"player_name":"Pedro Eliezer Rodr\u00edguez Ledesma","vaep_value":0.1932311255,"offensive_value":0.1061825791,"defensive_value":0.0870485464,"count":42},"11":{"player_id":14748,"player_name":"Nicol\u00e1s Hern\u00e1n Otamendi","vaep_value":0.0637096767,"offensive_value":0.0414628069,"defensive_value":0.0222468699,"count":61},"12":{"player_id":14808,"player_name":"Eden Hazard","vaep_value":0.2595168483,"offensive_value":0.2196232197,"defensive_value":0.0398936286,"count":178},"13":{"player_id":25553,"player_name":"Kyle Walker","vaep_value":0.1206465482,"offensive_value":0.067047431,"defensive_value":0.0535991172,"count":72},"14":{"player_id":25707,"player_name":"Ederson Santana de Moraes","vaep_value":0.0319371193,"offensive_value":0.0131639245,"defensive_value":0.0187731949,"count":30},"15":{"player_id":26010,"player_name":"Aymeric  Laporte","vaep_value":-0.0299064377,"offensive_value":-0.0293454933,"defensive_value":-0.0005609444,"count":2},"16":{"player_id":38021,"player_name":"Oleksandr Zinchenko","vaep_value":0.2502395507,"offensive_value":0.2505149441,"defensive_value":-0.0002753934,"count":97},"17":{"player_id":40787,"player_name":"Aymeric  Laporte","vaep_value":-0.0060820431,"offensive_value":-0.0036434145,"defensive_value":-0.0024386286,"count":1},"18":{"player_id":70083,"player_name":"Nicol\u00e1s Hern\u00e1n Otamendi","vaep_value":0.016245713,"offensive_value":0.0118401051,"defensive_value":0.0044056079,"count":3},"19":{"player_id":70086,"player_name":"Kevin De Bruyne","vaep_value":0.2851880325,"offensive_value":0.2299379108,"defensive_value":0.0552501217,"count":141},"20":{"player_id":71654,"player_name":"Oleksandr Zinchenko","vaep_value":0.0657090544,"offensive_value":0.0663051114,"defensive_value":-0.000596057,"count":30},"21":{"player_id":105333,"player_name":"Leroy San\u00e9","vaep_value":0.008623058,"offensive_value":0.0099851096,"defensive_value":-0.0013620516,"count":16},"22":{"player_id":134502,"player_name":"David Josu\u00e9 Jim\u00e9nez Silva","vaep_value":0.1680185322,"offensive_value":0.1412409376,"defensive_value":0.0267775946,"count":101},"23":{"player_id":135103,"player_name":"\u0130lkay G\u00fcndo\u011fan","vaep_value":0.0842264427,"offensive_value":0.0213332913,"defensive_value":0.0628931514,"count":41},"24":{"player_id":241564,"player_name":"Oleksandr Zinchenko","vaep_value":0.1277206011,"offensive_value":0.1054073022,"defensive_value":0.0223132989,"count":168},"25":{"player_id":245364,"player_name":"\u0130lkay G\u00fcndo\u011fan","vaep_value":-0.0758550924,"offensive_value":-0.070721921,"defensive_value":-0.0051331713,"count":60},"26":{"player_id":265673,"player_name":"Aymeric  Laporte","vaep_value":0.722304947,"offensive_value":0.7513331971,"defensive_value":-0.0290282501,"count":59},"27":{"player_id":340386,"player_name":"Nicol\u00e1s Hern\u00e1n Otamendi","vaep_value":-0.007314073,"offensive_value":-0.0052290675,"defensive_value":-0.0020850055,"count":2}}