{"0":{"player_id":0,"player_name":"Moise Bioty Kean","vaep_value":0.0380399388,"offensive_value":0.0266299309,"defensive_value":0.0114100078,"count":9},"1":{"player_id":192,"player_name":"Bruno Petkovi\u0107","vaep_value":0.8038580596,"offensive_value":0.8105825034,"defensive_value":-0.0067244439,"count":25},"2":{"player_id":3736,"player_name":"Marcel B\u00fcchel","vaep_value":0.0231862799,"offensive_value":0.0257880851,"defensive_value":-0.0026018051,"count":4},"3":{"player_id":20403,"player_name":"Cristiano Biraghi","vaep_value":0.038423553,"offensive_value":0.0223660506,"defensive_value":0.0160575024,"count":7},"4":{"player_id":20414,"player_name":"Alex Ferrari","vaep_value":0.1687001867,"offensive_value":0.153394779,"defensive_value":0.0153054077,"count":39},"5":{"player_id":20663,"player_name":"Cristiano Biraghi","vaep_value":-0.0297192305,"offensive_value":-0.0243744163,"defensive_value":-0.0053448142,"count":22},"6":{"player_id":20866,"player_name":"Alex Ferrari","vaep_value":0.1838324115,"offensive_value":0.0514655557,"defensive_value":0.1323668557,"count":92},"7":{"player_id":20935,"player_name":"Alex Ferrari","vaep_value":0.7400494105,"offensive_value":0.638490167,"defensive_value":0.1015592435,"count":49},"8":{"player_id":20949,"player_name":"Bruno Petkovi\u0107","vaep_value":0.5205851957,"offensive_value":0.3302461393,"defensive_value":0.1903390564,"count":34},"9":{"player_id":21025,"player_name":"Bruno Petkovi\u0107","vaep_value":0.1273088013,"offensive_value":0.1205312926,"defensive_value":0.0067775086,"count":27},"10":{"player_id":21298,"player_name":"Cristiano Biraghi","vaep_value":0.1267906361,"offensive_value":0.2751280648,"defensive_value":-0.1483374287,"count":41},"11":{"player_id":21842,"player_name":"Marco Sportiello","vaep_value":0.0642730502,"offensive_value":0.1219391427,"defensive_value":-0.0576660925,"count":86},"12":{"player_id":22093,"player_name":"Jordan Veretout","vaep_value":0.0303237097,"offensive_value":0.0027936123,"defensive_value":0.0275300974,"count":20},"13":{"player_id":22099,"player_name":"Germ\u00e1n Alejandro Pezzella","vaep_value":-0.0638362219,"offensive_value":-0.0456602891,"defensive_value":-0.0181759328,"count":33},"14":{"player_id":22313,"player_name":"Jordan Veretout","vaep_value":0.4879945696,"offensive_value":0.3338299158,"defensive_value":0.1541646537,"count":85},"15":{"player_id":22380,"player_name":"Davide Astori","vaep_value":-0.1450159589,"offensive_value":-0.0831535258,"defensive_value":-0.0618624331,"count":19},"16":{"player_id":23705,"player_name":"Davide Astori","vaep_value":0.1128193152,"offensive_value":0.0271585125,"defensive_value":0.0856608027,"count":21},"17":{"player_id":25541,"player_name":"Mohamed Salim Fares","vaep_value":0.2218763804,"offensive_value":0.2275963537,"defensive_value":-0.0057199734,"count":95},"18":{"player_id":26373,"player_name":"Giovanni Pablo Simeone","vaep_value":-0.0651412217,"offensive_value":-0.0999110006,"defensive_value":0.0347697788,"count":13},"19":{"player_id":69400,"player_name":"Nicolas David Andrade ","vaep_value":0.1911774741,"offensive_value":0.1566419936,"defensive_value":0.0345354805,"count":88},"20":{"player_id":86328,"player_name":"Antonio Aldo Caracciolo","vaep_value":0.1353018811,"offensive_value":0.1605999122,"defensive_value":-0.025298031,"count":56},"21":{"player_id":252589,"player_name":"Antonio Aldo Caracciolo","vaep_value":0.1689980186,"offensive_value":0.1722845281,"defensive_value":-0.0032865095,"count":21},"22":{"player_id":263433,"player_name":"Mohamed Salim Fares","vaep_value":1.1449604088,"offensive_value":1.133637869,"defensive_value":0.0113225398,"count":51},"23":{"player_id":269152,"player_name":"Marco Benassi","vaep_value":-0.1945053536,"offensive_value":-0.1630835844,"defensive_value":-0.0314217692,"count":25},"24":{"player_id":328336,"player_name":"Jago\u0161 Vukovi\u0107","vaep_value":-0.1203003899,"offensive_value":0.0160819341,"defensive_value":-0.136382324,"count":39},"25":{"player_id":338249,"player_name":"Cristiano Biraghi","vaep_value":0.8146172122,"offensive_value":0.8245810401,"defensive_value":-0.0099638279,"count":33},"26":{"player_id":410031,"player_name":"Milan Badelj","vaep_value":1.5072712853,"offensive_value":1.5346793411,"defensive_value":-0.0274080558,"count":24},"27":{"player_id":424241,"player_name":"Milan Badelj","vaep_value":0.0520306433,"offensive_value":0.0410778286,"defensive_value":0.0109528147,"count":15},"28":{"player_id":447804,"player_name":"Alex Ferrari","vaep_value":0.0769354042,"offensive_value":0.0941515033,"defensive_value":-0.0172160991,"count":50}}