{"0":{"player_id":0,"player_name":"Moussa Konat\u00e9","vaep_value":0.0160291292,"offensive_value":0.0148413205,"defensive_value":0.0011878087,"count":4},"1":{"player_id":20685,"player_name":"Lucas Pedro Alves De Lima","vaep_value":0.0191082738,"offensive_value":0.0077269978,"defensive_value":0.011381276,"count":9},"2":{"player_id":25492,"player_name":"Adrien Thomasson","vaep_value":0.1896391355,"offensive_value":0.0697201714,"defensive_value":0.1199189641,"count":63},"3":{"player_id":25523,"player_name":"Adrien Thomasson","vaep_value":0.0739362361,"offensive_value":0.0307695968,"defensive_value":0.0431666393,"count":54},"4":{"player_id":25605,"player_name":"Ga\u00ebl Kakuta","vaep_value":0.939000388,"offensive_value":0.9264001225,"defensive_value":0.0126002656,"count":43},"5":{"player_id":26134,"player_name":"Thomas Monconduit","vaep_value":0.0364889795,"offensive_value":0.0775736826,"defensive_value":-0.0410847032,"count":66},"6":{"player_id":26276,"player_name":"Thomas Monconduit","vaep_value":0.132928661,"offensive_value":0.0765856851,"defensive_value":0.0563429758,"count":48},"7":{"player_id":26384,"player_name":"Andrei Girotto","vaep_value":0.2845540724,"offensive_value":0.3367898511,"defensive_value":-0.0522357787,"count":68},"8":{"player_id":26583,"player_name":"Emiliano Sala","vaep_value":0.1413007227,"offensive_value":0.1933004644,"defensive_value":-0.0519997417,"count":45},"9":{"player_id":28073,"player_name":"Bakaye Dibassy","vaep_value":-0.1844574268,"offensive_value":-0.1218709024,"defensive_value":-0.0625865244,"count":43},"10":{"player_id":28948,"player_name":"R\u00e9gis Gurtner","vaep_value":0.0058528053,"offensive_value":0.0266883989,"defensive_value":-0.0208355936,"count":14},"11":{"player_id":30320,"player_name":"Harisson Manzala","vaep_value":0.1220414272,"offensive_value":0.0805298397,"defensive_value":0.0415115874,"count":63},"12":{"player_id":38095,"player_name":"Harisson Manzala","vaep_value":-0.2020897556,"offensive_value":-0.1542331292,"defensive_value":-0.0478566265,"count":34},"13":{"player_id":40301,"player_name":"L\u00e9o Dubois","vaep_value":0.3339690061,"offensive_value":0.3628591642,"defensive_value":-0.0288901581,"count":79},"14":{"player_id":43515,"player_name":"Bakaye Dibassy","vaep_value":-0.0015118651,"offensive_value":-0.0231951096,"defensive_value":0.0216832445,"count":32},"15":{"player_id":83574,"player_name":"L\u00e9o Dubois","vaep_value":0.1242096343,"offensive_value":0.1812567583,"defensive_value":-0.057047124,"count":36},"16":{"player_id":97582,"player_name":"Santy Ngom","vaep_value":-0.0378367638,"offensive_value":-0.0227789087,"defensive_value":-0.0150578551,"count":13},"17":{"player_id":101795,"player_name":"R\u00e9gis Gurtner","vaep_value":-0.1901056112,"offensive_value":-0.1727826495,"defensive_value":-0.0173229617,"count":9},"18":{"player_id":105523,"player_name":"Prince-D\u00e9sir Gouano","vaep_value":0.2425413582,"offensive_value":0.291123196,"defensive_value":-0.0485818378,"count":76},"19":{"player_id":132972,"player_name":"Bongani Zungu","vaep_value":0.065246293,"offensive_value":0.0678745415,"defensive_value":-0.0026282485,"count":3},"20":{"player_id":209028,"player_name":"Bakaye Dibassy","vaep_value":0.0863423116,"offensive_value":-0.0202670803,"defensive_value":0.1066093919,"count":77},"21":{"player_id":214710,"player_name":"Thomas Monconduit","vaep_value":0.1327139509,"offensive_value":0.1104757607,"defensive_value":0.0222381903,"count":63},"22":{"player_id":217872,"player_name":"Prince-D\u00e9sir Gouano","vaep_value":-0.0258552135,"offensive_value":-0.0002495605,"defensive_value":-0.0256056529,"count":21},"23":{"player_id":217874,"player_name":"Prince-D\u00e9sir Gouano","vaep_value":-0.1347128226,"offensive_value":-0.0967714621,"defensive_value":-0.0379413605,"count":51},"24":{"player_id":229198,"player_name":"Valentin Rongier","vaep_value":-0.0438332295,"offensive_value":-0.0192681251,"defensive_value":-0.0245651044,"count":46},"25":{"player_id":242446,"player_name":"Oualid El Hajjam","vaep_value":0.1367824854,"offensive_value":0.213471369,"defensive_value":-0.0766888836,"count":77},"26":{"player_id":244357,"player_name":"Adrien Thomasson","vaep_value":-0.0702327733,"offensive_value":-0.0704150847,"defensive_value":0.0001823114,"count":49},"27":{"player_id":260002,"player_name":"Lucas Pedro Alves De Lima","vaep_value":0.2212808122,"offensive_value":0.1772223124,"defensive_value":0.0440584998,"count":102},"28":{"player_id":364772,"player_name":"Lucas Pedro Alves De Lima","vaep_value":0.0325368959,"offensive_value":0.0008787215,"defensive_value":0.0316581745,"count":1}}